pypixels/__init__.py
pypixels-0.0.1.dist-info/WHEEL
pypixels-0.0.1.dist-info/METADATA
pypixels-0.0.1.dist-info/RECORD
