Metadata-Version: 2.1
Name: pypixels
Version: 0.0.1
Summary: A Python interface for the Python Discord's Pixels project.
License: MIT
Author: vcokltfre
Author-email: vcokltfre@gmail.com
Requires-Python: >=3.8,<4.0
Classifier: License :: OSI Approved :: MIT License
Classifier: Programming Language :: Python :: 3
Classifier: Programming Language :: Python :: 3.8
Classifier: Programming Language :: Python :: 3.9
Requires-Dist: Pillow (>=8.2.0,<9.0.0)
Requires-Dist: aiohttp (>=3.7.4,<4.0.0)
Requires-Dist: loguru (>=0.5.3,<0.6.0)
